kvargs.py
kvargs-0.3.2.dist-info/LICENSE
kvargs-0.3.2.dist-info/METADATA
kvargs-0.3.2.dist-info/WHEEL
kvargs-0.3.2.dist-info/top_level.txt
kvargs-0.3.2.dist-info/RECORD
