Metadata-Version: 2.1
Name: kvargs
Version: 0.3.2
Summary: Key-value command line argument parser
Home-page: https://declassed.art/repository/kvargs
Author: AXY
Author-email: axy@declassed.art
License: UNKNOWN
Platform: UNKNOWN
Classifier: Programming Language :: Python :: 3
Classifier: License :: OSI Approved :: BSD License
Classifier: Operating System :: OS Independent
Classifier: Intended Audience :: Developers
Classifier: Development Status :: 5 - Production/Stable
Classifier: Topic :: Software Development :: User Interfaces
Requires-Python: >=3.6
